typing_aliases/__init__.py
typing_aliases/py.typed
typing_aliases/typing.py
typing_aliases-1.10.0.dist-info/LICENSE
typing_aliases-1.10.0.dist-info/METADATA
typing_aliases-1.10.0.dist-info/WHEEL
typing_aliases-1.10.0.dist-info/RECORD
